{
  "nouns": {
    "first": [
      {
        "word": "rose",
        "gender": "feminine",
        "conjugations": {
          "singular": {
            "nominative": "rosa",
            "genetive": "rosae",
            "dative": "rosae",
            "accusative": "rosam",
            "ablative": "rosā"
          },
          "plural": {
            "nominative": "rosae",
            "genetive": "rosārum",
            "dative": "rosīs",
            "accusative": "rosam",
            "ablative": "rosīs"
          }
        }
      }
    ],
    "second": [
      {
        "word": "gift",
        "gender": "neuter",
        "conjugations": {
          "singular": {
            "nominative": "dōnum",
            "genetive": "dōnī",
            "dative": "dōnō",
            "accusative": "dōnum",
            "ablative": "dōnō"
          },
          "plural": {
            "nominative": "dōna",
            "genetive": "dōnōrum",
            "dative": "dōnīs",
            "accusative": "dōna",
            "ablative": "dōnīs"
          }
        }
      }
    ]
  }
}
